zibanu/django/logging/__init__.py
zibanu/django/logging/admin.py
zibanu/django/logging/admin_views.py
zibanu/django/logging/apps.py
zibanu/django/logging/models.py
zibanu/django/logging/lib/__init__.py
zibanu/django/logging/lib/receivers.py
zibanu/django/logging/lib/signals.py
zibanu/django/logging/lib/handlers/__init__.py
zibanu/django/logging/lib/handlers/db_handler.py
zibanu/django/logging/lib/utils/__init__.py
zibanu/django/logging/lib/utils/signals_factory.py
zibanu/django/logging/locale/es/LC_MESSAGES/django.mo
zibanu/django/logging/locale/es/LC_MESSAGES/django.po
zibanu/django/logging/migrations/0001_initial.py
zibanu/django/logging/migrations/0002_maillog.py
zibanu/django/logging/migrations/0003_log_detail.py
zibanu/django/logging/migrations/0004_alter_log_detail.py
zibanu/django/logging/migrations/0005_alter_log_user_alter_maillog_smtp_error.py
zibanu/django/logging/migrations/0006_auditentity.py
zibanu/django/logging/migrations/__init__.py
zibanu_django_logging-1.2.3.dist-info/LICENSE
zibanu_django_logging-1.2.3.dist-info/METADATA
zibanu_django_logging-1.2.3.dist-info/WHEEL
zibanu_django_logging-1.2.3.dist-info/top_level.txt
zibanu_django_logging-1.2.3.dist-info/RECORD
