Metadata-Version: 2.2
Name: zibanu-django-logging
Version: 1.2.3
Summary: Zibanu logging library for django projects
Author-email: Mario Cerón <mario.ceron@cqinversiones.co>
License:                     GNU GENERAL PUBLIC LICENSE
Keywords: django,zibanu,library
Classifier: License :: OSI Approved :: GNU General Public License v3 (GPLv3)
Classifier: Programming Language :: Python :: 3.9
Classifier: Development Status :: 4 - Beta
Classifier: Framework :: Django
Classifier: Framework :: Django :: 4.1
Classifier: Environment :: Web Environment
Classifier: Operating System :: OS Independent
Classifier: Topic :: Internet :: WWW/HTTP
Requires-Python: >=3.9
License-File: LICENSE
Requires-Dist: Django>=3.2
Requires-Dist: djangorestframework
Requires-Dist: djangorestframework-simplejwt
Requires-Dist: zibanu-django>=1.3.0
